[
    {
        "question": "You are a math expert. When you respond, respond only with the Solution of the final Problem, thinking step by step. At the end of the Solution, when you give your final answer, write it in the form \"\\boxed{$answer$}. I hope it is correct.\"\nLet $\\mathbf{v} = \\begin{pmatrix} 2 \\\\ 1 \\\\ -1 \\end{pmatrix}$ and $\\mathbf{w} = \\begin{pmatrix} 1 \\\\ 0 \\\\ 3 \\end{pmatrix}.$  The columns of a matrix are $\\mathbf{u},$ $\\mathbf{v},$ and $\\mathbf{w},$ where $\\mathbf{u}$ is a unit vector.  Find the largest possible determinant of the matrix.",
        "inference": "Let the matrix be $A = [\\mathbf{u}, \\mathbf{v}, \\mathbf{w}]$. The determinant of $A$ is given by\n\\begin{align*} \\det(A) &= \\det([\\mathbf{u}, \\mathbf{v}, \\mathbf{w}]) \\\\ &= \\mathbf{u} \\cdot (\\mathbf{v} \\times \\mathbf{w}) \\end{align*}The vector $\\mathbf{v} \\times \\mathbf{w}$ is\n\\begin{align*} \\mathbf{v} \\times \\mathbf{w} &= \\begin{pmatrix} 2 \\\\ 1 \\\\ -1 \\end{pmatrix} \\times \\begin{pmatrix} 1 \\\\ 0 \\\\ 3 \\end{pmatrix} \\\\ &= \\begin{pmatrix} (1)(3) - (0)(-1) \\\\ (-1)(1) - (2)(3) \\\\ (2)(0) - (1)(1) \\end{pmatrix} \\\\ &= \\begin{pmatrix} 3 \\\\ -7 \\\\ -1 \\end{pmatrix}. \\end{align*}Then\n\\begin{align*} |\\mathbf{u} \\cdot (\\mathbf{v} \\times \\mathbf{w})| &= |\\mathbf{u}| |\\mathbf{v} \\times \\mathbf{w}| \\cos \\theta \\\\ &= |\\mathbf{v} \\times \\mathbf{w}| |\\cos \\theta| \\end{align*}Since $|\\mathbf{u}| = 1$, the largest possible value of $\\mathbf{u} \\cdot (\\mathbf{v} \\times \\mathbf{w})$ is when $\\mathbf{u}$ is in the same direction as $\\mathbf{v} \\times \\mathbf{w}$, which means $\\cos \\theta = 1.$  Then\n\\[ |\\mathbf{v} \\times \\mathbf{w}| = \\left\\| \\begin{pmatrix} 3 \\\\ -7 \\\\ -1 \\end{pmatrix} \\right\\| = \\sqrt{3^2 + (-7)^2 + (-1)^2} = \\sqrt{9 + 49 + 1} = \\sqrt{59}. \\]Therefore, the largest possible value of the determinant is $\\sqrt{59}.$\n\n\\boxed{$\\sqrt{59}$}. I hope it is correct.\n",
        "ground_truth": "The determinant of the matrix is given by the scalar triple product\n\\[\\mathbf{u} \\cdot (\\mathbf{v} \\times \\mathbf{w}) = \\mathbf{u} \\cdot \\begin{pmatrix} 3 \\\\ -7 \\\\ -1 \\end{pmatrix}.\\]In turn, this is equal to\n\\[\\mathbf{u} \\cdot \\begin{pmatrix} 3 \\\\ -7 \\\\ -1 \\end{pmatrix} = \\|\\mathbf{u}\\| \\left\\| \\begin{pmatrix} 3 \\\\ -7 \\\\ -1 \\end{pmatrix} \\right\\| \\cos \\theta = \\sqrt{59} \\cos \\theta,\\]where $\\theta$ is the angle between $\\mathbf{u}$ and $\\begin{pmatrix} 3 \\\\ -7 \\\\ -1 \\end{pmatrix}.$\n\nHence, the maximum value of the determinant is $\\boxed{\\sqrt{59}},$ and this is achieved when $\\mathbf{u}$ is the unit vector pointing in the direction of $\\begin{pmatrix} 3 \\\\ -7 \\\\ -1 \\end{pmatrix}.$"
    },
    {
        "question": "Let the matrix be $A = [\\mathbf{u}, \\mathbf{v}, \\mathbf{w}]$. The determinant of $A$ is given by\n\\begin{align*} \\det(A) &= \\det([\\mathbf{u}, \\mathbf{v}, \\mathbf{w}]) \\\\ &= \\mathbf{u} \\cdot (\\mathbf{v} \\times \\mathbf{w}) \\end{align*}The vector $\\mathbf{v} \\times \\mathbf{w}$ is\n\\begin{align*} \\mathbf{v} \\times \\mathbf{w} &= \\begin{pmatrix} 2 \\\\ 1 \\\\ -1 \\end{pmatrix} \\times \\begin{pmatrix} 1 \\\\ 0 \\\\ 3 \\end{pmatrix} \\\\ &= \\begin{pmatrix} (1)(3) - (0)(-1) \\\\ (-1)(1) - (2)(3) \\\\ (2)(0) - (1)(1) \\end{pmatrix} \\\\ &= \\begin{pmatrix} 3 \\\\ -7 \\\\ -1 \\end{pmatrix}. \\end{align*}Then\n\\begin{align*} |\\mathbf{u} \\cdot (\\mathbf{v} \\times \\mathbf{w})| &= |\\mathbf{u}| |\\mathbf{v} \\times \\mathbf{w}| \\cos \\theta \\\\ &= |\\mathbf{v} \\times \\mathbf{w}| |\\cos \\theta| \\end{align*}Since $|\\mathbf{u}| = 1$, the largest possible value of $\\mathbf{u} \\cdot (\\mathbf{v} \\times \\mathbf{w})$ is when $\\mathbf{u}$ is in the same direction as $\\mathbf{v} \\times \\mathbf{w}$, which means $\\cos \\theta = 1.$  Then\n\\[ |\\mathbf{v} \\times \\mathbf{w}| = \\left\\| \\begin{pmatrix} 3 \\\\ -7 \\\\ -1 \\end{pmatrix} \\right\\| = \\sqrt{3^2 + (-7)^2 + (-1)^2} = \\sqrt{9 + 49 + 1} = \\sqrt{59}. \\]Therefore, the largest possible value of the determinant is $\\sqrt{59}.$\n\n\\boxed{$\\sqrt{59}$}. I hope it is correct.\n\nThere might be an error in the solution above because of lack of understanding of the question. Please correct the error, if any, and rewrite the solution. Only output the final solution! At the end of the Solution, when you give your final answer, write it in the form \"\\boxed{$answer$}. I hope it is correct.\"",
        "inference": "$\\sqrt{59}$\n\n\\boxed{$\\sqrt{59}$}. I hope it is correct.\n",
        "ground_truth": "The determinant of the matrix is given by the scalar triple product\n\\[\\mathbf{u} \\cdot (\\mathbf{v} \\times \\mathbf{w}) = \\mathbf{u} \\cdot \\begin{pmatrix} 3 \\\\ -7 \\\\ -1 \\end{pmatrix}.\\]In turn, this is equal to\n\\[\\mathbf{u} \\cdot \\begin{pmatrix} 3 \\\\ -7 \\\\ -1 \\end{pmatrix} = \\|\\mathbf{u}\\| \\left\\| \\begin{pmatrix} 3 \\\\ -7 \\\\ -1 \\end{pmatrix} \\right\\| \\cos \\theta = \\sqrt{59} \\cos \\theta,\\]where $\\theta$ is the angle between $\\mathbf{u}$ and $\\begin{pmatrix} 3 \\\\ -7 \\\\ -1 \\end{pmatrix}.$\n\nHence, the maximum value of the determinant is $\\boxed{\\sqrt{59}},$ and this is achieved when $\\mathbf{u}$ is the unit vector pointing in the direction of $\\begin{pmatrix} 3 \\\\ -7 \\\\ -1 \\end{pmatrix}.$"
    }
]